theme/__init__.py
theme/__main__.py
theme/commands.py
theme/shop.py
npc_shopify_cli-0.0.7.dist-info/LICENSE
npc_shopify_cli-0.0.7.dist-info/METADATA
npc_shopify_cli-0.0.7.dist-info/WHEEL
npc_shopify_cli-0.0.7.dist-info/top_level.txt
npc_shopify_cli-0.0.7.dist-info/RECORD
